typed_graphene/__init__.py
typed_graphene/typed_field.py
typed_graphene/typed_mutation.py
typed_graphene/utils.py
typed_graphene/transformers/__init__.py
typed_graphene/transformers/base_transformer.py
typed_graphene/transformers/bool_transformer.py
typed_graphene/transformers/date_transformer.py
typed_graphene/transformers/datetime_transformer.py
typed_graphene/transformers/decimal_transformer.py
typed_graphene/transformers/float_transformer.py
typed_graphene/transformers/int_transformer.py
typed_graphene/transformers/register.py
typed_graphene/transformers/str_transformer.py
typed_graphene-0.0.4.dist-info/LICENSE
typed_graphene-0.0.4.dist-info/METADATA
typed_graphene-0.0.4.dist-info/WHEEL
typed_graphene-0.0.4.dist-info/top_level.txt
typed_graphene-0.0.4.dist-info/RECORD
