Metadata-Version: 2.1
Name: typed-graphene
Version: 0.0.4
Summary: Type-safe interface for graphene-python.
Author: Jeong Yeon Nam<tonynamy@apperz.co.kr>
License: MIT
Project-URL: Source, https://github.com/tonynamy/typed-graphene
Project-URL: Documentation, https://github.com/tonynamy/typed-graphene
Project-URL: Tracker, https://github.com/tonynamy/typed-graphene/issues
License-File: LICENSE
